colcon_hardware_acceleration/__init__.py
colcon_hardware_acceleration/subverb/__init__.py
colcon_hardware_acceleration/subverb/board.py
colcon_hardware_acceleration/subverb/emulation.py
colcon_hardware_acceleration/subverb/hls.py
colcon_hardware_acceleration/subverb/hypervisor.py
colcon_hardware_acceleration/subverb/linux.py
colcon_hardware_acceleration/subverb/list.py
colcon_hardware_acceleration/subverb/mkinitramfs.py
colcon_hardware_acceleration/subverb/mount.py
colcon_hardware_acceleration/subverb/platform.py
colcon_hardware_acceleration/subverb/select.py
colcon_hardware_acceleration/subverb/umount.py
colcon_hardware_acceleration/subverb/version.py
colcon_hardware_acceleration/subverb/vpp.py
colcon_hardware_acceleration/verb/__init__.py
colcon_hardware_acceleration/verb/acceleration.py
publish_python/__init__.py
publish_python/cli.py
publish_python/config.py
publish_python/package.py
publish_python/registry.py
publish_python/artifact/__init__.py
publish_python/artifact/stdeb.py
publish_python/artifact/wheel.py
publish_python/upload/__init__.py
publish_python/upload/github.py
publish_python/upload/packagecloud.py
publish_python/upload/pypi.py
colcon_hardware_acceleration-0.7.0.dist-info/LICENSE
colcon_hardware_acceleration-0.7.0.dist-info/METADATA
colcon_hardware_acceleration-0.7.0.dist-info/WHEEL
colcon_hardware_acceleration-0.7.0.dist-info/entry_points.txt
colcon_hardware_acceleration-0.7.0.dist-info/top_level.txt
colcon_hardware_acceleration-0.7.0.dist-info/zip-safe
colcon_hardware_acceleration-0.7.0.dist-info/RECORD
