Metadata-Version: 2.1
Name: colcon-hardware-acceleration
Version: 0.7.0
Summary: Extension for colcon to include hardware acceleration
Home-page: https://colcon.readthedocs.io
Author: Víctor Mayoral-Vilches
Author-email: victor@accelerationrobotics.com
Maintainer: Víctor Mayoral-Vilches
Maintainer-email: victor@accelerationrobotics.com
License: Apache License, Version 2.0
Project-URL: GitHub, https://github.com/ros-acceleration/colcon-hardware-acceleration
Project-URL: Changelog, https://github.com/ros-acceleration/colcon-hardware-acceleration/blob/main/CHANGELOG.rst
Keywords: colcon
Platform: UNKNOWN
Classifier: Development Status :: 3 - Alpha
Classifier: Environment :: Plugins
Classifier: Intended Audience :: Developers
Classifier: License :: OSI Approved :: Apache Software License
Classifier: Operating System :: POSIX
Classifier: Programming Language :: Python
Classifier: Topic :: Software Development :: Build Tools
Requires-Dist: colcon-core (>=0.5.2)
